odin_vision/__init__.py
odin_vision/chronicle_utils.py
odin_vision/cli.py
odin_vision/COMMANDS.md
odin_vision/constants.py
odin_vision/dataset.py
odin_vision/dataset_classification.py
odin_vision/dataset_detection.py
odin_vision/project_utils.py
odin_vision/results.py
odin_vision/start.py
odin_vision/training.py
odin_vision/training_classification.py
odin_vision/training_detection.py
odin_vision-1.1.6.dist-info/entry_points.txt
odin_vision-1.1.6.dist-info/METADATA
odin_vision-1.1.6.dist-info/WHEEL
odin_vision-1.1.6.dist-info/RECORD
