Metadata-Version: 2.1
Name: odin-vision
Version: 1.1.6
Summary: Odin is an open-source CLI framework for managing big computer vision projects that are based on YOLO.
Author: Matheus J G Silva
Author-email: matjsz42@gmail.com
Requires-Python: >=3.12,<4.0
Classifier: Programming Language :: Python :: 3
Classifier: Programming Language :: Python :: 3.12
Classifier: Programming Language :: Python :: 3.13
Requires-Dist: albumentations (>=1.4.23,<2.0.0)
Requires-Dist: click (>=8.1.8,<9.0.0)
Requires-Dist: colorama (>=0.4.6,<0.5.0)
Requires-Dist: matplotlib (>=3.10.0,<4.0.0)
Requires-Dist: notebook (>=7.3.1,<8.0.0)
Requires-Dist: polars (>=1.17.1,<2.0.0)
Requires-Dist: torch (==2.5.1)
Requires-Dist: ultralytics (>=8.3.51,<9.0.0)
